corsid/MWIS.py
corsid/__init__.py
corsid/annotation.py
corsid/corsid.py
corsid/corsid_annot.py
corsid/heuristic.py
corsid/solution.py
corsid/util.py
corsid/xgboost_model.json
corsid-0.1.3.data/scripts/corsid
corsid-0.1.3.data/scripts/corsid_a
corsid-0.1.3.dist-info/LICENSE
corsid-0.1.3.dist-info/METADATA
corsid-0.1.3.dist-info/WHEEL
corsid-0.1.3.dist-info/top_level.txt
corsid-0.1.3.dist-info/RECORD
