Metadata-Version: 2.1
Name: corsid
Version: 0.1.3
Summary: Core Sequence Identifier
Home-page: http://github.com/elkebir-group/CORSID
Author: Chuanyi Zhang
Author-email: chuanyi5@illinois.edu
License: MIT
Requires-Python: >=3.7
License-File: LICENSE
Requires-Dist: numpy
Requires-Dist: pysam
Requires-Dist: pandas
Requires-Dist: pytablewriter
Requires-Dist: tqdm
Requires-Dist: xgboost
Requires-Dist: sklearn
